Metadata-Version: 2.4
Name: PyLOpt
Version: 1.0.0
Summary: PyLevel Optimisation: A Python library for bilevel optimisation
Author-email: "Florian Thaler, Thomas Pock" <florian.thaler@tugraz.at>
Maintainer-email: Florian Thaler <florian.thaler@tugraz.at>
License-Expression: MIT
Project-URL: Homepage, https://github.com/VLOGroup/pylopt
Keywords: PyLOpt,Bilevel optimisation,Image reconstruction
Classifier: Programming Language :: Python :: 3
Requires-Dist: torch>=2.6.0
Requires-Dist: torchvision>=0.21.0
Requires-Dist: numpy>=2.0.0
Requires-Dist: confuse>=2.0.1
Requires-Dist: scipy>=1.15.2
Requires-Dist: opencv-python-headless>=4.11.0.86
Requires-Dist: matplotlib>=3.10.1
Requires-Dist: PyQt5>=5.15.11
Requires-Dist: pillow>=11.1.0
Requires-Dist: ninja>=1.13.0
Requires-Dist: quartic_bspline_extension>=0.3.0
